timerdec/__init__.py
timerdec/decorators.py
timerdec/shared_data.py
timerdec/snapshots.py
timerdec-0.0.4.dist-info/LICENSE
timerdec-0.0.4.dist-info/METADATA
timerdec-0.0.4.dist-info/WHEEL
timerdec-0.0.4.dist-info/top_level.txt
timerdec-0.0.4.dist-info/RECORD
