Metadata-Version: 2.1
Name: timerdec
Version: 0.0.4
Summary: Simple decorators for measuring Python methods execution time
Home-page: https://github.com/desmoteo/timerdec
Author: Matteo Ferrabone
Author-email: matteo.ferrabone@gmail.com
License: MIT
Platform: UNKNOWN
Classifier: Programming Language :: Python :: 3
Classifier: License :: OSI Approved :: MIT License
Classifier: Operating System :: OS Independent
Classifier: Intended Audience :: Developers
Classifier: Intended Audience :: System Administrators
Classifier: Intended Audience :: Information Technology
Classifier: Topic :: Utilities 
Requires-Python: >=3.6
Requires-Dist: psutil
Requires-Dist: tqdm
